AUTHORS.rst
CONTRIBUTING.rst
HISTORY.rst
LICENSE
MANIFEST.in
README.rst
setup.cfg
setup.py
huey_drf_api.egg-info/PKG-INFO
huey_drf_api.egg-info/SOURCES.txt
huey_drf_api.egg-info/dependency_links.txt
huey_drf_api.egg-info/not-zip-safe
huey_drf_api.egg-info/top_level.txt
hueydrfapi/__init__.py
hueydrfapi/api.py
hueydrfapi/apps.py
hueydrfapi/exceptions.py
hueydrfapi/models.py
hueydrfapi/serializers.py
hueydrfapi/urls.py
hueydrfapi/views.py
hueydrfapi/static/css/hueydrfapi.css
hueydrfapi/static/js/hueydrfapi.js
hueydrfapi/templates/hueydrfapi/base.html