Metadata-Version: 1.1
Name: huey-drf-api
Version: 0.2.0
Summary: A DRF API for Huey
Home-page: https://github.com/eyemyth/huey-drf-api
Author: Jay Thompson
Author-email: jay_thompson@wgbh.org
License: MIT
Keywords: huey-drf-api
Platform: UNKNOWN
Classifier: Development Status :: 3 - Alpha
Classifier: Framework :: Django :: 2.0
Classifier: Intended Audience :: Developers
Classifier: License :: OSI Approved :: BSD License
Classifier: Natural Language :: English
Classifier: Programming Language :: Python :: 3
Classifier: Programming Language :: Python :: 3.5
Classifier: Programming Language :: Python :: 3.6
Classifier: Programming Language :: Python :: 3.7
